pytoolkit/__init__.py
pytoolkit/_version.py
pytoolkit/data.py
pytoolkit/decorate.py
pytoolkit/static.py
pytoolkit/exceptions/__init__.py
pytoolkit/keys/__init__.py
pytoolkit/py_cert/__init__.py
pytoolkit/py_cert/cacert.py
pytoolkit/py_mailer/__init__.py
pytoolkit/py_mailer/mailer.py
pytoolkit/py_splunk/__init__.py
pytoolkit/py_splunk/splunk.py
pytoolkit/utilities/__init__.py
pytoolkit/utilities/files.py
pytoolkit/utilities/inet.py
pytoolkit/utilities/pkg_utils.py
pytoolkit/utilities/utils.py
pytoolkit/utilities/dicts/flatten.py
pytoolkit/utilities/dicts/roundtrip.py
pytoolkit/utilities/dicts/unflatten.py
pytoolkit928-1.0.1.dist-info/licenses/LICENSE
pytoolkit928-1.0.1.dist-info/METADATA
pytoolkit928-1.0.1.dist-info/WHEEL
pytoolkit928-1.0.1.dist-info/top_level.txt
pytoolkit928-1.0.1.dist-info/RECORD
