Metadata-Version: 2.4
Name: pytoolkit928
Version: 1.0.1
Summary: A General Use Python Tookit.
Author-email: atav928 <dev@tavnets.com>
License: GNU GENERAL PUBLIC LICENSE
Project-URL: Homepage, https://www.tavnets.com/blog/python-toolkit/
Project-URL: Repository, https://github.com/atav928/pytoolkit
Project-URL: Changelog, https://github.com/atav928/pytoolkit928/blob/main/CHANGELOG.md
Keywords: utilities,splunk,dataclasses,toolkit
Classifier: License :: OSI Approved :: MIT License
Classifier: Programming Language :: Python :: Implementation
Classifier: Programming Language :: Python :: 3.10
Classifier: Programming Language :: Python :: 3.11
Requires-Python: <4,>=3.7
License-File: LICENSE
Requires-Dist: certifi
Requires-Dist: decorator
Requires-Dist: pathlib
Requires-Dist: dataclasses
Requires-Dist: PyYaml
Requires-Dist: pandas
Requires-Dist: numpy>=1.22.2
Requires-Dist: airportsdata>=20231230
Requires-Dist: requests>=2.32.0
Requires-Dist: urllib3>=2.2.2
Provides-Extra: test
Requires-Dist: pytest-cov; extra == "test"
Requires-Dist: pytest; extra == "test"
Requires-Dist: pytest-mock; extra == "test"
Requires-Dist: unittest2; extra == "test"
Requires-Dist: dataclasses; extra == "test"
Requires-Dist: six; extra == "test"
Requires-Dist: black; extra == "test"
Requires-Dist: isort; extra == "test"
Requires-Dist: autoflake; extra == "test"
Requires-Dist: safety; extra == "test"
Requires-Dist: tomli; extra == "test"
Requires-Dist: pylint; extra == "test"
Dynamic: license-file
